<PAMDataset>
  <Metadata>
    <MDI key="Description">Band1: Depth prediction at zero hydrographic level, Band2: Interpolated deviation map (prediction - true) with nearest method</MDI>
    <MDI key="ImageName">S2A_MSIL1C_20180305T230901</MDI>
    <MDI key="Model">Ridge(alpha=0.00059411339849650333, copy_X=True, fit_intercept=True,
   max_iter=None, normalize=False, random_state=None, solver='auto',
   tol=0.001)</MDI>
    <MDI key="Model_coefficients">{'Red/ExtraRed': '8.0621513246213450', 'Green/ExtraRed': '-0.9747853365148582', 'Blue/ExtraRed': '-5.7057452511632318', 'ExtraBlue/ExtraRed': '0.6702767064612847', 'Green/Red': '6.3511606682807713', 'Blue/Red': '3.5553088194331530', 'ExtraBlue/Red': '2.6408822654999082', 'Blue/Green': '4.6314948686138546', 'ExtraBlue/Green': '-0.6605683662552575', 'ExtraBlue/Blue': '-3.7536477788444591'}</MDI>
    <MDI key="Model_intercepts">-14.9433818415593258</MDI>
    <MDI key="R2_score">0.906318195089</MDI>
    <MDI key="RMaxS">0.498642821921</MDI>
    <MDI key="RMedS">0.0101205702586</MDI>
    <MDI key="RMinS">6.59581973697e-08</MDI>
    <MDI key="RMS">0.0300730925219</MDI>
    <MDI key="tr_R2_score">0.908970576815</MDI>
    <MDI key="tr_RMaxS">0.494157836835</MDI>
    <MDI key="tr_RMedS">0.00981547680367</MDI>
    <MDI key="tr_RMinS">4.84159318365e-08</MDI>
    <MDI key="tr_RMS">0.0292216430743</MDI>
  </Metadata>
  <PAMRasterBand band="1">
    <Histograms>
      <HistItem>
        <HistMin>-3.5255136936903</HistMin>
        <HistMax>5.423735901713371</HistMax>
        <BucketCount>1000</BucketCount>
        <IncludeOutOfRange>0</IncludeOutOfRange>
        <Approximate>1</Approximate>
        <HistCounts>1|1|0|0|0|0|0|0|0|0|0|0|0|0|0|0|0|0|0|0|0|0|0|0|1|0|0|0|1|0|0|0|0|0|0|0|0|0|0|0|0|0|0|0|1|0|0|0|0|0|1|1|0|1|0|0|0|0|0|0|1|0|1|1|0|1|0|0|1|0|0|1|0|0|0|0|0|1|0|3|0|0|0|0|1|0|0|0|0|2|0|3|2|0|1|2|0|2|1|0|2|1|4|1|1|1|1|1|5|0|1|2|2|1|0|2|4|1|2|3|2|4|2|2|1|3|4|5|6|2|5|9|4|7|9|1|4|9|4|1|4|3|7|3|1|3|2|3|3|3|1|2|2|6|1|1|7|1|4|3|3|6|4|11|12|9|10|9|6|10|16|8|7|9|12|14|11|9|15|6|9|12|12|11|12|9|10|11|14|12|15|13|15|9|17|13|8|12|12|15|16|9|13|14|8|15|18|8|13|25|19|12|17|11|13|15|19|19|26|21|15|23|17|16|16|23|20|24|24|12|23|26|26|23|30|22|35|26|31|31|26|36|29|33|33|30|34|41|45|34|44|38|40|55|35|45|38|47|46|38|50|42|53|38|42|58|62|63|40|47|47|65|52|57|43|58|60|53|57|64|61|56|67|74|54|73|78|73|74|109|75|86|75|73|109|101|81|85|82|105|106|91|114|100|92|116|117|99|124|128|133|131|139|143|113|139|118|125|128|110|115|131|135|125|126|136|138|137|150|149|131|151|152|165|165|184|177|153|163|148|170|161|149|170|183|182|184|196|166|215|218|193|184|234|193|236|217|222|188|197|206|214|197|218|227|214|202|202|201|211|245|204|228|200|224|200|200|195|190|207|173|192|176|213|173|208|187|186|189|177|196|190|187|203|208|208|215|238|231|205|224|238|225|229|228|238|235|265|280|241|241|246|246|246|238|229|233|212|224|227|249|231|280|229|241|226|253|227|233|244|202|225|208|197|197|213|204|201|186|199|175|162|143|181|184|152|146|158|160|135|169|133|146|110|142|136|131|138|143|130|154|128|122|136|136|140|145|134|127|125|139|146|133|130|140|127|125|149|132|153|157|143|158|156|152|134|151|156|130|161|144|136|157|123|135|151|133|144|154|143|147|135|129|124|140|138|121|149|117|160|142|122|155|145|148|130|130|113|137|143|128|140|118|145|107|142|144|142|160|155|123|152|125|146|126|153|160|152|155|149|155|172|157|161|154|156|171|144|157|173|142|168|163|166|136|146|152|164|141|150|160|153|137|151|153|178|153|154|173|137|146|152|160|148|170|157|155|119|140|151|153|166|155|152|164|157|168|139|142|163|159|163|167|143|138|134|146|141|130|159|124|128|162|146|141|149|148|152|135|144|141|124|140|138|135|145|135|139|134|131|134|128|114|137|112|121|115|111|116|97|98|114|104|80|102|87|82|96|79|90|82|105|91|93|83|91|87|87|75|67|74|84|70|77|65|64|59|67|63|68|67|53|64|63|69|76|60|72|69|69|48|53|59|36|32|52|48|39|58|50|42|49|50|37|43|44|48|44|40|40|38|41|43|42|32|36|45|30|37|37|40|44|46|47|36|33|36|31|35|23|26|42|31|20|27|29|27|35|29|34|31|24|41|32|24|36|27|28|28|35|37|24|20|34|33|19|21|35|27|27|33|22|29|20|25|34|30|19|19|17|22|33|31|20|31|19|20|18|25|25|23|27|22|19|30|23|22|18|22|17|20|22|13|20|18|26|27|15|13|20|16|16|20|25|21|23|16|12|20|14|13|12|19|14|14|8|20|26|19|16|23|22|17|14|17|9|5|10|18|11|27|21|18|16|20|15|15|12|16|9|15|15|12|9|7|4|14|12|6|11|9|11|10|9|9|9|8|7|6|9|9|16|5|5|9|7|11|10|5|13|6|9|4|5|11|11|5|2|5|6|5|4|7|7|3|8|4|6|3|6|7|7|4|7|5|6|4|2|3|4|2|4|2|2|3|3|3|3|0|1|2|1|3|2|2|4|1|1|3|2|2|0|1|2|1|0|1|1|0|5|1|1|3|0|0|0|1|0|0|0|0|0|1|1|0|0|2|0|0|4|1|0|0|0|0|0|1|0|1|0|0|0|0|0|1|0|0|0|0|0|0|1|0|0|0|0|1|0|0|0|0|0|0|0|0|0|0|0|0|0|0|0|0|0|1|0|0|0|0|0|0|0|0|0|0|0|0|0|0|0|0|0|0|0|0|0|0|0|0|1</HistCounts>
      </HistItem>
    </Histograms>
    <Metadata>
      <MDI key="STATISTICS_MAXIMUM">5.4192657470703</MDI>
      <MDI key="STATISTICS_MEAN">0.69453981921363</MDI>
      <MDI key="STATISTICS_MINIMUM">-3.5210435390472</MDI>
      <MDI key="STATISTICS_STDDEV">1.1829173665326</MDI>
    </Metadata>
  </PAMRasterBand>
  <PAMRasterBand band="2">
    <Histograms>
      <HistItem>
        <HistMin>-0.4735306912511587</HistMin>
        <HistMax>0.5292093270868064</HistMax>
        <BucketCount>1000</BucketCount>
        <IncludeOutOfRange>0</IncludeOutOfRange>
        <Approximate>1</Approximate>
        <HistCounts>13|0|0|0|0|0|0|0|0|0|0|0|0|0|0|0|0|0|0|0|0|0|0|0|0|0|0|0|0|27|0|0|0|0|0|0|0|0|0|5|0|0|0|0|0|0|0|0|0|0|0|0|0|0|0|0|0|0|0|0|0|0|0|0|0|0|0|0|0|0|0|0|0|0|0|0|0|0|0|0|0|0|0|0|0|0|0|0|0|0|0|0|0|0|0|0|0|0|0|0|0|0|0|0|0|0|0|0|0|0|0|0|0|0|0|0|0|0|0|0|0|0|0|0|0|0|0|0|0|0|0|0|0|0|0|0|0|0|0|0|0|0|0|0|0|39|0|0|0|0|0|0|0|0|0|0|0|0|0|0|0|0|0|0|0|0|1|0|0|0|0|0|0|0|0|0|0|0|0|0|0|0|0|0|0|0|0|0|0|0|0|0|0|0|0|0|0|0|0|0|0|0|0|2|0|0|0|0|0|0|0|0|0|0|0|0|0|8|0|0|0|0|0|0|0|0|0|0|0|0|11|0|0|5|0|0|0|0|0|0|0|9|0|0|0|0|0|0|0|9|28|0|0|0|8|0|0|0|0|0|0|0|0|0|0|0|40|7|0|8|0|0|0|0|0|0|0|0|0|14|0|14|0|0|0|0|0|0|0|0|0|0|0|0|0|0|0|9|0|0|0|0|0|0|0|11|0|0|0|0|0|0|0|0|0|3|0|0|0|0|0|0|0|0|0|0|0|0|0|0|11|0|0|0|0|26|0|0|0|0|0|3|0|0|0|0|11|0|0|0|0|0|0|0|0|0|0|4|0|0|0|0|0|0|0|3|0|0|0|0|12|0|0|0|0|17|0|95|0|0|0|0|10|0|0|0|0|0|0|17|0|0|0|27|0|0|18|0|0|0|7|0|0|1|0|0|0|0|0|4|0|0|0|26|3|0|43|0|32|0|15|0|9|0|0|0|0|0|0|0|5|0|0|17|0|12|3|0|8|0|0|0|0|0|0|19|46|0|9|0|0|0|0|0|0|0|0|0|0|0|41|5|0|1|0|1|0|15|0|0|0|0|0|0|0|0|7|0|108|0|10|0|0|0|8|0|0|4|0|0|0|0|0|0|0|0|0|18|6|2|6|29|0|0|0|0|0|0|0|25|0|0|0|0|0|0|0|9|0|0|0|3|6|0|0|0|0|0|0|0|0|0|0|0|0|1|16|0|0|1|0|3|5|0|3|0|5|0|0|0|0|0|0|0|0|0|0|0|0|0|0|0|0|0|0|0|0|0|0|0|0|0|0|0|0|0|0|23|0|0|0|2|0|0|0|0|8|17|14|0|0|0|0|0|24|0|6|0|4|0|0|3|0|0|0|0|37|0|0|0|0|0|0|0|0|0|0|0|0|0|0|0|0|0|0|0|0|0|0|0|0|6|0|0|30|23|0|0|0|0|0|0|0|0|0|0|69|0|0|0|0|0|0|0|0|0|0|0|0|0|0|0|0|7|0|0|0|0|0|0|0|0|0|0|0|7|0|0|0|0|0|0|0|0|0|0|0|14|0|0|0|0|0|0|0|0|0|3|0|0|0|0|0|0|0|0|0|0|0|0|0|0|0|0|0|0|0|0|0|0|0|0|0|0|0|11|0|0|0|0|0|0|0|0|0|0|0|0|0|0|0|0|0|0|0|0|0|0|1|0|0|0|0|0|0|0|0|0|0|0|0|0|0|0|0|0|0|0|0|0|0|0|0|1|0|0|0|0|0|0|0|0|0|0|0|0|0|0|0|0|0|0|0|0|0|0|0|0|0|10|0|0|0|0|0|0|0|0|0|0|0|0|0|0|0|0|0|0|0|0|0|0|0|0|0|0|0|0|0|2|0|0|0|0|0|0|0|0|0|0|83|0|0|0|0|0|0|0|0|0|0|0|0|0|0|0|0|0|0|0|0|0|0|0|0|0|0|0|0|0|0|0|0|0|0|0|0|0|0|0|0|0|0|0|0|0|0|0|0|0|0|0|0|0|0|0|0|0|0|0|0|0|0|0|0|0|0|0|0|0|0|0|0|0|0|0|0|0|0|0|0|0|0|0|0|0|0|0|0|0|0|0|0|0|0|0|0|0|0|0|0|0|0|0|0|0|0|0|0|0|0|0|0|0|0|0|0|0|0|0|0|0|0|0|0|0|0|0|0|0|0|0|0|0|0|0|0|0|0|0|0|0|0|0|0|0|0|0|0|0|0|0|0|0|0|0|0|0|0|10</HistCounts>
      </HistItem>
    </Histograms>
    <Metadata>
      <MDI key="STATISTICS_MAXIMUM">0.52870845794678</MDI>
      <MDI key="STATISTICS_MEAN">-0.0097961147884168</MDI>
      <MDI key="STATISTICS_MINIMUM">-0.47302982211113</MDI>
      <MDI key="STATISTICS_STDDEV">0.17764797783278</MDI>
    </Metadata>
  </PAMRasterBand>
</PAMDataset>
